basictextmetrics/__init__.py
basictextmetrics/core.py
BasicTextMetrics-0.2.1.dist-info/LICENSE
BasicTextMetrics-0.2.1.dist-info/METADATA
BasicTextMetrics-0.2.1.dist-info/WHEEL
BasicTextMetrics-0.2.1.dist-info/top_level.txt
BasicTextMetrics-0.2.1.dist-info/RECORD
