Metadata-Version: 2.1
Name: BasicTextMetrics
Version: 0.2.1
Summary: Analyze textual data and extract useful metrics such as word count, character count, average word length, and most common words
Author-email: Famosa Muyiwa <nenling19@gmail.com>
License: MIT License
Project-URL: Source, https://github.com/famosamuyiwa/TextMetrics.git
Keywords: Text analysis,Text metrics,Word counting,Character counting,Word length,Frequency analysis,Linguistic analysis,Natural language processing (NLP),Textual data processing,Textual insights,Textual statistics,Textual analytics,Language metrics,Language analysis,Text readability,Sentiment analysis (potentially),Tokenization,Part-of-speech tagging (PoS tagging),Textual summarization,Lexical analysis
Classifier: Development Status :: 3 - Alpha
Classifier: Operating System :: OS Independent
Classifier: License :: OSI Approved :: MIT License
Classifier: Programming Language :: Python
Classifier: Programming Language :: Python :: 3
Requires-Python: >=3.6
License-File: LICENSE
Requires-Dist: nltk
